xhs_crawl/__init__.py
xhs_crawl/cli.py
xhs_crawl/models.py
xhs_crawl/spider.py
xhs_crawl-0.1.5.dist-info/LICENSE
xhs_crawl-0.1.5.dist-info/METADATA
xhs_crawl-0.1.5.dist-info/WHEEL
xhs_crawl-0.1.5.dist-info/entry_points.txt
xhs_crawl-0.1.5.dist-info/RECORD
