Metadata-Version: 2.1
Name: xhs-crawl
Version: 0.1.5
Summary: 一个异步的小红书爬虫工具，支持笔记内容和图片的批量下载
License: MIT
Keywords: spider,crawler,xiaohongshu,download
Author: LGrok
Author-email: luolin.work@gmail.com
Requires-Python: >=3.9,<4.0
Classifier: Development Status :: 4 - Beta
Classifier: Environment :: Console
Classifier: Intended Audience :: Developers
Classifier: License :: OSI Approved :: MIT License
Classifier: Programming Language :: Python :: 3
Classifier: Programming Language :: Python :: 3.9
Classifier: Programming Language :: Python :: 3.10
Classifier: Programming Language :: Python :: 3.11
Classifier: Programming Language :: Python :: 3.12
Classifier: Programming Language :: Python :: 3.13
Classifier: Topic :: Internet :: WWW/HTTP :: Dynamic Content
Classifier: Topic :: Software Development :: Libraries :: Python Modules
Requires-Dist: aiofiles (>=23.2.1,<24.0.0)
Requires-Dist: beautifulsoup4 (>=4.12.3,<5.0.0)
Requires-Dist: fake-useragent (>=1.4.0,<2.0.0)
Requires-Dist: httpx (>=0.25.2,<0.26.0)
Requires-Dist: loguru (>=0.7.2,<0.8.0)
Requires-Dist: pydantic (>=2.6.1,<3.0.0)
Requires-Dist: tenacity (>=8.2.3,<9.0.0)
Project-URL: Bug Tracker, https://github.com/LinLL/xhs-crawl/issues
Project-URL: Homepage, https://github.com/LinLL/xhs-crawl
